photolink/__init__.py
photolink/aio.py
photolink/api.py
photolink/exceptions.py
photolink/utils.py
photolink-1.0.3.dist-info/LICENSE
photolink-1.0.3.dist-info/METADATA
photolink-1.0.3.dist-info/WHEEL
photolink-1.0.3.dist-info/top_level.txt
photolink-1.0.3.dist-info/RECORD
