Metadata-Version: 2.1
Name: photolink
Version: 1.0.3
Summary: PhotoLink API wrapper
Home-page: https://github.com/xudoberdigayratov/PhotoLink
Download-URL: https://github.com/xudoberdigayratov/PhotoLink.git
Author: Xudoberdi G'ayratov
Author-email: gayratov@xudoberdi.uz
License: MIT
Classifier: License :: OSI Approved :: MIT License
Classifier: Operating System :: OS Independent
Classifier: Programming Language :: Python
Classifier: Programming Language :: Python :: 3
Classifier: Programming Language :: Python :: 3.7
Classifier: Programming Language :: Python :: 3.8
Classifier: Programming Language :: Python :: 3.9
Classifier: Programming Language :: Python :: 3.10
Classifier: Programming Language :: Python :: 3.11
License-File: LICENSE
Requires-Dist: requests
Requires-Dist: filetype
Provides-Extra: aio
Requires-Dist: httpx ; extra == 'aio'
Requires-Dist: filetype ; extra == 'aio'
